CHANGES.txt
MANIFEST.in
README.txt
gtkeggdeps.py
setup.py
./gtkeggdeps.py
gtkeggdeps.egg-info/PKG-INFO
gtkeggdeps.egg-info/SOURCES.txt
gtkeggdeps.egg-info/dependency_links.txt
gtkeggdeps.egg-info/entry_points.txt
gtkeggdeps.egg-info/not-zip-safe
gtkeggdeps.egg-info/requires.txt
gtkeggdeps.egg-info/top_level.txt