Metadata-Version: 1.0
Name: gtkeggdeps
Version: 0.0.7
Summary: Interactive egg dependency browser
Home-page: http://mg.pov.lt/gtkeggdeps/
Author: Marius Gedminas
Author-email: marius@gedmin.as
License: ZPL 2.1
Download-URL: http://cheeseshop.python.org/pypi/gtkeggdeps
Platform: UNKNOWN
Classifier: Development Status :: 3 - Alpha
Classifier: Environment :: X11 Applications :: GTK
Classifier: Intended Audience :: Developers
Classifier: License :: OSI Approved :: Zope Public License
Classifier: Programming Language :: Python
Classifier: Natural Language :: English
Classifier: Operating System :: OS Independent
Classifier: Topic :: Software Development
